{
  "name": "dungeons_arise:fungi/mushroom_mines/mushroom_mines_spawners",
  "fallback": "minecraft:empty",
  "elements": [
    {
      "weight": 1,
      "element": {
        "location": "dungeons_arise:mushroom_mines/mushroom_mines_skeleton_ranged_0",
        "processors": "minecraft:empty",
        "projection": "rigid",
        "element_type": "minecraft:single_pool_element"
      }
    },
    {
      "weight": 1,
      "element": {
        "location": "dungeons_arise:mushroom_mines/mushroom_mines_zombie_armored_0",
        "processors": "minecraft:empty",
        "projection": "rigid",
        "element_type": "minecraft:single_pool_element"
      }
    },
    {
      "weight": 1,
      "element": {
        "location": "dungeons_arise:mushroom_mines/mushroom_mines_zombie_armored_1",
        "processors": "minecraft:empty",
        "projection": "rigid",
        "element_type": "minecraft:single_pool_element"
      }
    }
  ]
}